arxivit.py
arxivit-0.7.1.dist-info/METADATA
arxivit-0.7.1.dist-info/WHEEL
arxivit-0.7.1.dist-info/entry_points.txt
arxivit-0.7.1.dist-info/licenses/LICENSE
arxivit-0.7.1.dist-info/RECORD
