Metadata-Version: 2.4
Name: arxivit
Version: 0.7.1
Summary: Robust arXiv LaTeX cleaner with DPI-based image rescaling.
Project-URL: Source Code, https://github.com/kabouzeid/arxivit
Author-email: Karim Abou Zeid <contact@ka.codes>
License-File: LICENSE
Requires-Python: >=3.10
Requires-Dist: humanize>=4.12.1
Requires-Dist: pathspec>=0.12.1
Requires-Dist: pillow>=11.1.0
Requires-Dist: rich>=13.9.4
